<annotation>
    <folder>simple</folder>
    <filename>frame812.jpg</filename>
    <path>/home/yusuf/Documents/GitHub/Tracking_Project/MaskR-CNN/Gen_Dataset/simple/frame812.jpg</path>
    <source>
        <database>Unknown</database>
    </source>
    <size>
        <width>1280</width>
        <height>960</height>
        <depth>3</depth>
    </size>
    <segmented>0</segmented>
    <object>
        <name>fly</name>
        <pose>Unspecified</pose>
        <truncated>0</truncated>
        <difficult>0</difficult>
        <bndbox>
            <xmin>211</xmin>
            <ymin>49</ymin>
            <xmax>236</xmax>
            <ymax>74</ymax>
        </bndbox>
    </object>    <object>
        <name>fly</name>
        <pose>Unspecified</pose>
        <truncated>0</truncated>
        <difficult>0</difficult>
        <bndbox>
            <xmin>291</xmin>
            <ymin>117</ymin>
            <xmax>316</xmax>
            <ymax>142</ymax>
        </bndbox>
    </object>    <object>
        <name>fly</name>
        <pose>Unspecified</pose>
        <truncated>0</truncated>
        <difficult>0</difficult>
        <bndbox>
            <xmin>359</xmin>
            <ymin>192</ymin>
            <xmax>384</xmax>
            <ymax>217</ymax>
        </bndbox>
    </object>    <object>
        <name>fly</name>
        <pose>Unspecified</pose>
        <truncated>0</truncated>
        <difficult>0</difficult>
        <bndbox>
            <xmin>609</xmin>
            <ymin>235</ymin>
            <xmax>634</xmax>
            <ymax>260</ymax>
        </bndbox>
    </object>    <object>
        <name>fly</name>
        <pose>Unspecified</pose>
        <truncated>0</truncated>
        <difficult>0</difficult>
        <bndbox>
            <xmin>921</xmin>
            <ymin>143</ymin>
            <xmax>946</xmax>
            <ymax>168</ymax>
        </bndbox>
    </object>    <object>
        <name>fly</name>
        <pose>Unspecified</pose>
        <truncated>0</truncated>
        <difficult>0</difficult>
        <bndbox>
            <xmin>1038</xmin>
            <ymin>70</ymin>
            <xmax>1063</xmax>
            <ymax>95</ymax>
        </bndbox>
    </object>    <object>
        <name>fly</name>
        <pose>Unspecified</pose>
        <truncated>0</truncated>
        <difficult>0</difficult>
        <bndbox>
            <xmin>762</xmin>
            <ymin>148</ymin>
            <xmax>787</xmax>
            <ymax>173</ymax>
        </bndbox>
    </object>    <object>
        <name>fly</name>
        <pose>Unspecified</pose>
        <truncated>0</truncated>
        <difficult>0</difficult>
        <bndbox>
            <xmin>1011</xmin>
            <ymin>111</ymin>
            <xmax>1036</xmax>
            <ymax>136</ymax>
        </bndbox>
    </object>    <object>
        <name>fly</name>
        <pose>Unspecified</pose>
        <truncated>0</truncated>
        <difficult>0</difficult>
        <bndbox>
            <xmin>361</xmin>
            <ymin>136</ymin>
            <xmax>386</xmax>
            <ymax>161</ymax>
        </bndbox>
    </object>    <object>
        <name>fly</name>
        <pose>Unspecified</pose>
        <truncated>0</truncated>
        <difficult>0</difficult>
        <bndbox>
            <xmin>412</xmin>
            <ymin>293</ymin>
            <xmax>437</xmax>
            <ymax>318</ymax>
        </bndbox>
    </object>    <object>
        <name>fly</name>
        <pose>Unspecified</pose>
        <truncated>0</truncated>
        <difficult>0</difficult>
        <bndbox>
            <xmin>699</xmin>
            <ymin>254</ymin>
            <xmax>724</xmax>
            <ymax>279</ymax>
        </bndbox>
    </object>    <object>
        <name>fly</name>
        <pose>Unspecified</pose>
        <truncated>0</truncated>
        <difficult>0</difficult>
        <bndbox>
            <xmin>771</xmin>
            <ymin>310</ymin>
            <xmax>796</xmax>
            <ymax>335</ymax>
        </bndbox>
    </object>    <object>
        <name>fly</name>
        <pose>Unspecified</pose>
        <truncated>0</truncated>
        <difficult>0</difficult>
        <bndbox>
            <xmin>408</xmin>
            <ymin>352</ymin>
            <xmax>433</xmax>
            <ymax>377</ymax>
        </bndbox>
    </object>    <object>
        <name>fly</name>
        <pose>Unspecified</pose>
        <truncated>0</truncated>
        <difficult>0</difficult>
        <bndbox>
            <xmin>1015</xmin>
            <ymin>87</ymin>
            <xmax>1040</xmax>
            <ymax>112</ymax>
        </bndbox>
    </object>    <object>
        <name>fly</name>
        <pose>Unspecified</pose>
        <truncated>0</truncated>
        <difficult>0</difficult>
        <bndbox>
            <xmin>828</xmin>
            <ymin>258</ymin>
            <xmax>853</xmax>
            <ymax>283</ymax>
        </bndbox>
    </object>    <object>
        <name>fly</name>
        <pose>Unspecified</pose>
        <truncated>0</truncated>
        <difficult>0</difficult>
        <bndbox>
            <xmin>1001</xmin>
            <ymin>46</ymin>
            <xmax>1026</xmax>
            <ymax>71</ymax>
        </bndbox>
    </object>    <object>
        <name>fly</name>
        <pose>Unspecified</pose>
        <truncated>0</truncated>
        <difficult>0</difficult>
        <bndbox>
            <xmin>913</xmin>
            <ymin>89</ymin>
            <xmax>938</xmax>
            <ymax>114</ymax>
        </bndbox>
    </object>    <object>
        <name>fly</name>
        <pose>Unspecified</pose>
        <truncated>0</truncated>
        <difficult>0</difficult>
        <bndbox>
            <xmin>379</xmin>
            <ymin>393</ymin>
            <xmax>404</xmax>
            <ymax>418</ymax>
        </bndbox>
    </object>    <object>
        <name>fly</name>
        <pose>Unspecified</pose>
        <truncated>0</truncated>
        <difficult>0</difficult>
        <bndbox>
            <xmin>433</xmin>
            <ymin>548</ymin>
            <xmax>458</xmax>
            <ymax>573</ymax>
        </bndbox>
    </object>    <object>
        <name>fly</name>
        <pose>Unspecified</pose>
        <truncated>0</truncated>
        <difficult>0</difficult>
        <bndbox>
            <xmin>550</xmin>
            <ymin>425</ymin>
            <xmax>575</xmax>
            <ymax>450</ymax>
        </bndbox>
    </object>    <object>
        <name>fly</name>
        <pose>Unspecified</pose>
        <truncated>0</truncated>
        <difficult>0</difficult>
        <bndbox>
            <xmin>523</xmin>
            <ymin>654</ymin>
            <xmax>548</xmax>
            <ymax>679</ymax>
        </bndbox>
    </object>    <object>
        <name>fly</name>
        <pose>Unspecified</pose>
        <truncated>0</truncated>
        <difficult>0</difficult>
        <bndbox>
            <xmin>908</xmin>
            <ymin>724</ymin>
            <xmax>933</xmax>
            <ymax>749</ymax>
        </bndbox>
    </object>    <object>
        <name>fly</name>
        <pose>Unspecified</pose>
        <truncated>0</truncated>
        <difficult>0</difficult>
        <bndbox>
            <xmin>400</xmin>
            <ymin>687</ymin>
            <xmax>425</xmax>
            <ymax>712</ymax>
        </bndbox>
    </object>    <object>
        <name>fly</name>
        <pose>Unspecified</pose>
        <truncated>0</truncated>
        <difficult>0</difficult>
        <bndbox>
            <xmin>808</xmin>
            <ymin>791</ymin>
            <xmax>833</xmax>
            <ymax>816</ymax>
        </bndbox>
    </object>    <object>
        <name>fly</name>
        <pose>Unspecified</pose>
        <truncated>0</truncated>
        <difficult>0</difficult>
        <bndbox>
            <xmin>687</xmin>
            <ymin>773</ymin>
            <xmax>712</xmax>
            <ymax>798</ymax>
        </bndbox>
    </object>    <object>
        <name>fly</name>
        <pose>Unspecified</pose>
        <truncated>0</truncated>
        <difficult>0</difficult>
        <bndbox>
            <xmin>539</xmin>
            <ymin>730</ymin>
            <xmax>564</xmax>
            <ymax>755</ymax>
        </bndbox>
    </object>    <object>
        <name>fly</name>
        <pose>Unspecified</pose>
        <truncated>0</truncated>
        <difficult>0</difficult>
        <bndbox>
            <xmin>349</xmin>
            <ymin>796</ymin>
            <xmax>374</xmax>
            <ymax>821</ymax>
        </bndbox>
    </object>    <object>
        <name>fly</name>
        <pose>Unspecified</pose>
        <truncated>0</truncated>
        <difficult>0</difficult>
        <bndbox>
            <xmin>997</xmin>
            <ymin>813</ymin>
            <xmax>1022</xmax>
            <ymax>838</ymax>
        </bndbox>
    </object>    <object>
        <name>fly</name>
        <pose>Unspecified</pose>
        <truncated>0</truncated>
        <difficult>0</difficult>
        <bndbox>
            <xmin>246</xmin>
            <ymin>842</ymin>
            <xmax>271</xmax>
            <ymax>867</ymax>
        </bndbox>
    </object>    <object>
        <name>fly</name>
        <pose>Unspecified</pose>
        <truncated>0</truncated>
        <difficult>0</difficult>
        <bndbox>
            <xmin>1044</xmin>
            <ymin>823</ymin>
            <xmax>1069</xmax>
            <ymax>848</ymax>
        </bndbox>
    </object>    <object>
        <name>fly</name>
        <pose>Unspecified</pose>
        <truncated>0</truncated>
        <difficult>0</difficult>
        <bndbox>
            <xmin>406</xmin>
            <ymin>801</ymin>
            <xmax>431</xmax>
            <ymax>826</ymax>
        </bndbox>
    </object>    <object>
        <name>fly</name>
        <pose>Unspecified</pose>
        <truncated>0</truncated>
        <difficult>0</difficult>
        <bndbox>
            <xmin>970</xmin>
            <ymin>64</ymin>
            <xmax>995</xmax>
            <ymax>89</ymax>
        </bndbox>
    </object>
</annotation>
